Metadata-Version: 2.1
Name: odoo14-addon-account_banking_ach_base
Version: 14.0.1.0.2
Summary: Add fields required for North American Banking & Financials
Home-page: https://github.com/OCA/l10n-usa
Author: Thinkwell Designs, Odoo Community Association (OCA)
Author-email: support@odoo-community.org
License: AGPL-3
Classifier: Programming Language :: Python
Classifier: Framework :: Odoo
Classifier: Framework :: Odoo :: 14.0
Classifier: License :: OSI Approved :: GNU Affero General Public License v3
Requires-Python: >=3.6
Requires-Dist: ach
Requires-Dist: odoo14-addon-account-banking-mandate
Requires-Dist: odoo14-addon-account-payment-order
Requires-Dist: odoo14-addon-l10n-us-partner-legal-number
Requires-Dist: odoo<14.1dev,>=14.0a
Requires-Dist: python-stdnum
